kimmdy_hydrolysis/__init__.py
kimmdy_hydrolysis/constants.py
kimmdy_hydrolysis/kimmdy-yaml-schema.json
kimmdy_hydrolysis/minisasa.py
kimmdy_hydrolysis/rates.py
kimmdy_hydrolysis/reaction.py
kimmdy_hydrolysis/utils.py
kimmdy_hydrolysis-0.5.1.dist-info/licenses/LICENSE
kimmdy_hydrolysis-0.5.1.dist-info/METADATA
kimmdy_hydrolysis-0.5.1.dist-info/WHEEL
kimmdy_hydrolysis-0.5.1.dist-info/entry_points.txt
kimmdy_hydrolysis-0.5.1.dist-info/top_level.txt
kimmdy_hydrolysis-0.5.1.dist-info/RECORD
