Metadata-Version: 2.4
Name: kimmdy-hydrolysis
Version: 0.5.1
Summary: Reaction plugin for KIMMDY that hydrolyses peptide bonds
Author-email: Jannik Buhr <jannik.m.buhr@gmail.com>
License: GPL-3.0
Classifier: Programming Language :: Python :: 3
Classifier: Operating System :: OS Independent
Requires-Python: >=3.10
License-File: LICENSE
Requires-Dist: MDAnalysis
Requires-Dist: kimmdy
Requires-Dist: freesasa
Provides-Extra: dev
Requires-Dist: pytest; extra == "dev"
Requires-Dist: pytest-cov; extra == "dev"
Requires-Dist: statsmodels; extra == "dev"
Requires-Dist: plotnine; extra == "dev"
Requires-Dist: pandas; extra == "dev"
Requires-Dist: numpy; extra == "dev"
Requires-Dist: tox; extra == "dev"
Requires-Dist: tox-uv; extra == "dev"
Requires-Dist: black; extra == "dev"
Requires-Dist: jupyter; extra == "dev"
Requires-Dist: griffe<1.0.0,>=0.33; extra == "dev"
Requires-Dist: quartodoc; extra == "dev"
Requires-Dist: kimmdy_grappa; extra == "dev"
Requires-Dist: grappa-ff; extra == "dev"
Requires-Dist: torch; extra == "dev"
Dynamic: license-file
